sem5/CV_vs_T.py
sem5/MBdistribution.py
sem5/__init__.py
sem5/clt1.py
sem5/clt_die_roll.py
sem5/coin_simulation.py
sem5/debye_plot.py
sem5/hist_random.py
sem5/mc_frac1.py
sem5/mc_fx2.py
sem5/mc_sin1.py
sem5/mcintegration.py
sem5/random_qs.py
sem5/temp_occupation.py
CU_SAM-0.0.1.dist-info/LICENSE
CU_SAM-0.0.1.dist-info/METADATA
CU_SAM-0.0.1.dist-info/WHEEL
CU_SAM-0.0.1.dist-info/top_level.txt
CU_SAM-0.0.1.dist-info/RECORD
